Metadata-Version: 1.1
Name: NLPnicer
Version: 1.1.1
Summary: NLPnicer helps you to handle abbreviation, emoji and spelling mistake in your text
Home-page: UNKNOWN
Author: Samarth Gupta
Author-email: samarthgupta0309@gmail.com
License: MIT
Keywords: NLPnicer
Platform: UNKNOWN
Classifier: Development Status :: 5 - Production/Stable
Classifier: Intended Audience :: Education
Classifier: Operating System :: Microsoft :: Windows :: Windows 10
Classifier: License :: OSI Approved :: MIT License
Classifier: Programming Language :: Python :: 3
